cloudenv/__init__.py
cloudenv/compat.py
cloudenv/main.py
cloudenv/version.py
cloudenv-0.2.8.dist-info/LICENSE
cloudenv-0.2.8.dist-info/METADATA
cloudenv-0.2.8.dist-info/WHEEL
cloudenv-0.2.8.dist-info/top_level.txt
cloudenv-0.2.8.dist-info/RECORD
