Metadata-Version: 2.1
Name: cloudenv
Version: 0.2.8
Summary: Keep Your Environmental Variables Secure And In Sync
Home-page: https://github.com/cloudenvhq/cloudenv-python/
Author: Lucas Carlson
Author-email: lucas@carlson.net
License: UNKNOWN
Platform: UNKNOWN
Classifier: Programming Language :: Python :: 3
Classifier: License :: OSI Approved :: MIT License
Classifier: Operating System :: OS Independent
Requires-Python: >=3.6
Requires-Dist: python-dotenv (>=0.15.0)
